Metadata-Version: 1.0
Name: logevo
Version: 0.0.2
Summary: Facke Logevo
Home-page: UNKNOWN
Author: UNKNOWN
Author-email: volodymyr.volodymyrovych@gmail.com
License: UNKNOWN
Platform: UNKNOWN
